freight/__init__.py
freight/admin.py
freight/app_settings.py
freight/apps.py
freight/auth_hooks.py
freight/constants.py
freight/forms.py
freight/helpers.py
freight/managers.py
freight/providers.py
freight/tasks.py
freight/urls.py
freight/views.py
freight/locale/django.pot
freight/locale/de/LC_MESSAGES/django.mo
freight/locale/de/LC_MESSAGES/django.po
freight/locale/en/LC_MESSAGES/django.mo
freight/locale/en/LC_MESSAGES/django.po
freight/locale/es/LC_MESSAGES/django.mo
freight/locale/es/LC_MESSAGES/django.po
freight/locale/fr_FR/LC_MESSAGES/django.mo
freight/locale/fr_FR/LC_MESSAGES/django.po
freight/locale/it_IT/LC_MESSAGES/django.mo
freight/locale/it_IT/LC_MESSAGES/django.po
freight/locale/ja/LC_MESSAGES/django.mo
freight/locale/ja/LC_MESSAGES/django.po
freight/locale/ko_KR/LC_MESSAGES/django.mo
freight/locale/ko_KR/LC_MESSAGES/django.po
freight/locale/ru/LC_MESSAGES/django.mo
freight/locale/ru/LC_MESSAGES/django.po
freight/locale/uk/LC_MESSAGES/django.mo
freight/locale/uk/LC_MESSAGES/django.po
freight/locale/zh_Hans/LC_MESSAGES/django.mo
freight/locale/zh_Hans/LC_MESSAGES/django.po
freight/migrations/0001_squashed.py
freight/migrations/0002_alter_contracthandler_last_error.py
freight/migrations/0003_improve_localization.py
freight/migrations/__init__.py
freight/models/__init__.py
freight/models/contract_handlers.py
freight/models/contracts.py
freight/models/routes.py
freight/static/freight/css/calculator.css
freight/static/freight/css/contracts.css
freight/static/freight/css/kalkoken.css
freight/static/freight/css/statistics.css
freight/static/freight/js/contracts.js
freight/static/freight/vendor/datatables/datetime.js
freight/templates/freight/add_location.html
freight/templates/freight/base.html
freight/templates/freight/calculator.html
freight/templates/freight/contracts_all.html
freight/templates/freight/contracts_user.html
freight/templates/freight/statistics.html
freight/templates/freight/partials/contract_table.html
aa_freight-2.0.0.dist-info/licenses/LICENSE
aa_freight-2.0.0.dist-info/WHEEL
aa_freight-2.0.0.dist-info/METADATA
aa_freight-2.0.0.dist-info/RECORD
